{
  "__inputs": [
    {
      "name": "DS_PROMETHEUS",
      "label": "Prometheus",
      "description": "",
      "type": "datasource",
      "pluginId": "prometheus",
      "pluginName": "Prometheus"
    }
  ],
  "__requires": [
    {
      "type": "grafana",
      "id": "grafana",
      "name": "Grafana",
      "version": "10.0.0"
    },
    {
      "type": "datasource",
      "id": "prometheus",
      "name": "Prometheus",
      "version": "1.0.0"
    },
    {
      "type": "panel",
      "id": "stat",
      "name": "Stat",
      "version": ""
    },
    {
      "type": "panel",
      "id": "timeseries",
      "name": "Time series",
      "version": ""
    }
  ],
  "id": null,
  "uid": "logging-pipeline-fluent",
  "title": "Logging Pipeline (Fluent Bit + Fluentd)",
  "description": "Monitoring dashboard for Fluent Bit and Fluentd logging pipeline",
  "tags": ["logging", "fluent-bit", "fluentd", "observability"],
  "timezone": "browser",
  "schemaVersion": 39,
  "version": 1,
  "editable": true,
  "graphTooltip": 1,
  "refresh": "30s",
  "time": {
    "from": "now-1h",
    "to": "now"
  },
  "templating": {
    "list": [
      {
        "current": {
          "selected": true,
          "text": ["All"],
          "value": ["$__all"]
        },
        "datasource": {
          "type": "prometheus",
          "uid": "prometheus"
        },
        "definition": "label_values(fluentbit_uptime, job)",
        "hide": 0,
        "includeAll": true,
        "label": "Fluent Bit Job",
        "multi": true,
        "name": "fb_job",
        "options": [],
        "query": {
          "query": "label_values(fluentbit_uptime, job)",
          "refId": "StandardVariableQuery"
        },
        "refresh": 2,
        "regex": "",
        "skipUrlSync": false,
        "sort": 1,
        "type": "query"
      },
      {
        "current": {
          "selected": true,
          "text": ["All"],
          "value": ["$__all"]
        },
        "datasource": {
          "type": "prometheus",
          "uid": "prometheus"
        },
        "definition": "label_values(fluentbit_uptime{job=~\"$fb_job\"}, instance)",
        "hide": 0,
        "includeAll": true,
        "label": "Fluent Bit Instance",
        "multi": true,
        "name": "fb_instance",
        "options": [],
        "query": {
          "query": "label_values(fluentbit_uptime{job=~\"$fb_job\"}, instance)",
          "refId": "StandardVariableQuery"
        },
        "refresh": 2,
        "regex": "",
        "skipUrlSync": false,
        "sort": 1,
        "type": "query"
      },
      {
        "current": {
          "selected": true,
          "text": ["All"],
          "value": ["$__all"]
        },
        "datasource": {
          "type": "prometheus",
          "uid": "prometheus"
        },
        "definition": "label_values(fluentd_output_status_buffer_total_bytes, job)",
        "hide": 0,
        "includeAll": true,
        "label": "Fluentd Job",
        "multi": true,
        "name": "fd_job",
        "options": [],
        "query": {
          "query": "label_values(fluentd_output_status_buffer_total_bytes, job)",
          "refId": "StandardVariableQuery"
        },
        "refresh": 2,
        "regex": "",
        "skipUrlSync": false,
        "sort": 1,
        "type": "query"
      },
      {
        "current": {
          "selected": true,
          "text": ["All"],
          "value": ["$__all"]
        },
        "datasource": {
          "type": "prometheus",
          "uid": "prometheus"
        },
        "definition": "label_values(fluentd_output_status_buffer_total_bytes{job=~\"$fd_job\"}, instance)",
        "hide": 0,
        "includeAll": true,
        "label": "Fluentd Instance",
        "multi": true,
        "name": "fd_instance",
        "options": [],
        "query": {
          "query": "label_values(fluentd_output_status_buffer_total_bytes{job=~\"$fd_job\"}, instance)",
          "refId": "StandardVariableQuery"
        },
        "refresh": 2,
        "regex": "",
        "skipUrlSync": false,
        "sort": 1,
        "type": "query"
      }
    ]
  },
  "annotations": {
    "list": [
      {
        "builtIn": 1,
        "datasource": {
          "type": "grafana",
          "uid": "-- Grafana --"
        },
        "enable": true,
        "hide": true,
        "iconColor": "rgba(0, 211, 255, 1)",
        "name": "Annotations & Alerts",
        "type": "dashboard"
      }
    ]
  },
  "panels": [
    {
      "type": "row",
      "title": "Overview",
      "collapsed": false,
      "gridPos": { "h": 1, "w": 24, "x": 0, "y": 0 },
      "id": 100,
      "panels": []
    },
    {
      "type": "stat",
      "title": "Fluent Bit Uptime",
      "id": 1,
      "datasource": {
        "type": "prometheus",
        "uid": "prometheus"
      },
      "gridPos": { "h": 4, "w": 4, "x": 0, "y": 1 },
      "fieldConfig": {
        "defaults": {
          "unit": "s",
          "thresholds": {
            "mode": "absolute",
            "steps": [
              { "color": "green", "value": null }
            ]
          },
          "color": { "mode": "thresholds" }
        },
        "overrides": []
      },
      "options": {
        "reduceOptions": {
          "values": false,
          "calcs": ["lastNotNull"],
          "fields": ""
        },
        "orientation": "auto",
        "textMode": "auto",
        "colorMode": "value",
        "graphMode": "none",
        "justifyMode": "auto"
      },
      "targets": [
        {
          "datasource": {
            "type": "prometheus",
            "uid": "prometheus"
          },
          "expr": "fluentbit_uptime{job=~\"$fb_job\",instance=~\"$fb_instance\"}",
          "refId": "A",
          "legendFormat": ""
        }
      ]
    },
    {
      "type": "stat",
      "title": "Input Records/sec",
      "id": 2,
      "datasource": {
        "type": "prometheus",
        "uid": "prometheus"
      },
      "gridPos": { "h": 4, "w": 4, "x": 4, "y": 1 },
      "fieldConfig": {
        "defaults": {
          "unit": "short",
          "thresholds": {
            "mode": "absolute",
            "steps": [
              { "color": "green", "value": null }
            ]
          },
          "color": { "mode": "thresholds" }
        },
        "overrides": []
      },
      "options": {
        "reduceOptions": {
          "values": false,
          "calcs": ["lastNotNull"],
          "fields": ""
        },
        "orientation": "auto",
        "textMode": "auto",
        "colorMode": "value",
        "graphMode": "area",
        "justifyMode": "auto"
      },
      "targets": [
        {
          "datasource": {
            "type": "prometheus",
            "uid": "prometheus"
          },
          "expr": "sum(rate(fluentbit_input_records_total{job=~\"$fb_job\",instance=~\"$fb_instance\"}[5m]))",
          "refId": "A",
          "legendFormat": ""
        }
      ]
    },
    {
      "type": "stat",
      "title": "Output Records/sec",
      "id": 3,
      "datasource": {
        "type": "prometheus",
        "uid": "prometheus"
      },
      "gridPos": { "h": 4, "w": 4, "x": 8, "y": 1 },
      "fieldConfig": {
        "defaults": {
          "unit": "short",
          "thresholds": {
            "mode": "absolute",
            "steps": [
              { "color": "green", "value": null }
            ]
          },
          "color": { "mode": "thresholds" }
        },
        "overrides": []
      },
      "options": {
        "reduceOptions": {
          "values": false,
          "calcs": ["lastNotNull"],
          "fields": ""
        },
        "orientation": "auto",
        "textMode": "auto",
        "colorMode": "value",
        "graphMode": "area",
        "justifyMode": "auto"
      },
      "targets": [
        {
          "datasource": {
            "type": "prometheus",
            "uid": "prometheus"
          },
          "expr": "sum(rate(fluentbit_output_proc_records_total{job=~\"$fb_job\",instance=~\"$fb_instance\"}[5m]))",
          "refId": "A",
          "legendFormat": ""
        }
      ]
    },
    {
      "type": "stat",
      "title": "Output Error Rate",
      "id": 4,
      "datasource": {
        "type": "prometheus",
        "uid": "prometheus"
      },
      "gridPos": { "h": 4, "w": 4, "x": 12, "y": 1 },
      "fieldConfig": {
        "defaults": {
          "unit": "short",
          "thresholds": {
            "mode": "absolute",
            "steps": [
              { "color": "green", "value": null },
              { "color": "red", "value": 1 }
            ]
          },
          "color": { "mode": "thresholds" }
        },
        "overrides": []
      },
      "options": {
        "reduceOptions": {
          "values": false,
          "calcs": ["lastNotNull"],
          "fields": ""
        },
        "orientation": "auto",
        "textMode": "auto",
        "colorMode": "value",
        "graphMode": "none",
        "justifyMode": "auto"
      },
      "targets": [
        {
          "datasource": {
            "type": "prometheus",
            "uid": "prometheus"
          },
          "expr": "sum(rate(fluentbit_output_errors_total{job=~\"$fb_job\",instance=~\"$fb_instance\"}[5m]))",
          "refId": "A",
          "legendFormat": ""
        }
      ]
    },
    {
      "type": "stat",
      "title": "Fluentd Buffer Size",
      "id": 5,
      "datasource": {
        "type": "prometheus",
        "uid": "prometheus"
      },
      "gridPos": { "h": 4, "w": 4, "x": 16, "y": 1 },
      "fieldConfig": {
        "defaults": {
          "unit": "bytes",
          "thresholds": {
            "mode": "absolute",
            "steps": [
              { "color": "green", "value": null }
            ]
          },
          "color": { "mode": "thresholds" }
        },
        "overrides": []
      },
      "options": {
        "reduceOptions": {
          "values": false,
          "calcs": ["lastNotNull"],
          "fields": ""
        },
        "orientation": "auto",
        "textMode": "auto",
        "colorMode": "value",
        "graphMode": "none",
        "justifyMode": "auto"
      },
      "targets": [
        {
          "datasource": {
            "type": "prometheus",
            "uid": "prometheus"
          },
          "expr": "sum(fluentd_output_status_buffer_total_bytes{job=~\"$fd_job\",instance=~\"$fd_instance\"})",
          "refId": "A",
          "legendFormat": ""
        }
      ]
    },
    {
      "type": "stat",
      "title": "Fluentd Errors",
      "id": 6,
      "datasource": {
        "type": "prometheus",
        "uid": "prometheus"
      },
      "gridPos": { "h": 4, "w": 4, "x": 20, "y": 1 },
      "fieldConfig": {
        "defaults": {
          "unit": "short",
          "thresholds": {
            "mode": "absolute",
            "steps": [
              { "color": "green", "value": null },
              { "color": "red", "value": 1 }
            ]
          },
          "color": { "mode": "thresholds" }
        },
        "overrides": []
      },
      "options": {
        "reduceOptions": {
          "values": false,
          "calcs": ["lastNotNull"],
          "fields": ""
        },
        "orientation": "auto",
        "textMode": "auto",
        "colorMode": "value",
        "graphMode": "none",
        "justifyMode": "auto"
      },
      "targets": [
        {
          "datasource": {
            "type": "prometheus",
            "uid": "prometheus"
          },
          "expr": "sum(fluentd_output_status_num_errors{job=~\"$fd_job\",instance=~\"$fd_instance\"})",
          "refId": "A",
          "legendFormat": ""
        }
      ]
    },
    {
      "type": "row",
      "title": "Fluent Bit Input",
      "collapsed": false,
      "gridPos": { "h": 1, "w": 24, "x": 0, "y": 5 },
      "id": 101,
      "panels": []
    },
    {
      "type": "timeseries",
      "title": "Input Bytes/sec (by name)",
      "id": 7,
      "datasource": {
        "type": "prometheus",
        "uid": "prometheus"
      },
      "gridPos": { "h": 8, "w": 8, "x": 0, "y": 6 },
      "fieldConfig": {
        "defaults": {
          "unit": "Bps",
          "custom": {
            "drawStyle": "line",
            "lineInterpolation": "smooth",
            "fillOpacity": 10,
            "gradientMode": "none",
            "spanNulls": false,
            "showPoints": "auto",
            "pointSize": 5,
            "stacking": { "mode": "none", "group": "A" },
            "axisPlacement": "auto",
            "lineWidth": 1
          },
          "color": { "mode": "palette-classic" },
          "thresholds": {
            "mode": "absolute",
            "steps": [
              { "color": "green", "value": null }
            ]
          }
        },
        "overrides": []
      },
      "options": {
        "tooltip": { "mode": "multi", "sort": "desc" },
        "legend": { "displayMode": "list", "placement": "bottom", "calcs": [] }
      },
      "targets": [
        {
          "datasource": {
            "type": "prometheus",
            "uid": "prometheus"
          },
          "expr": "rate(fluentbit_input_bytes_total{job=~\"$fb_job\",instance=~\"$fb_instance\"}[5m])",
          "refId": "A",
          "legendFormat": "{{name}}"
        }
      ]
    },
    {
      "type": "timeseries",
      "title": "Input Records/sec (by name)",
      "id": 8,
      "datasource": {
        "type": "prometheus",
        "uid": "prometheus"
      },
      "gridPos": { "h": 8, "w": 8, "x": 8, "y": 6 },
      "fieldConfig": {
        "defaults": {
          "unit": "short",
          "custom": {
            "drawStyle": "line",
            "lineInterpolation": "smooth",
            "fillOpacity": 10,
            "gradientMode": "none",
            "spanNulls": false,
            "showPoints": "auto",
            "pointSize": 5,
            "stacking": { "mode": "none", "group": "A" },
            "axisPlacement": "auto",
            "lineWidth": 1
          },
          "color": { "mode": "palette-classic" },
          "thresholds": {
            "mode": "absolute",
            "steps": [
              { "color": "green", "value": null }
            ]
          }
        },
        "overrides": []
      },
      "options": {
        "tooltip": { "mode": "multi", "sort": "desc" },
        "legend": { "displayMode": "list", "placement": "bottom", "calcs": [] }
      },
      "targets": [
        {
          "datasource": {
            "type": "prometheus",
            "uid": "prometheus"
          },
          "expr": "rate(fluentbit_input_records_total{job=~\"$fb_job\",instance=~\"$fb_instance\"}[5m])",
          "refId": "A",
          "legendFormat": "{{name}}"
        }
      ]
    },
    {
      "type": "timeseries",
      "title": "Storage Memory",
      "id": 9,
      "datasource": {
        "type": "prometheus",
        "uid": "prometheus"
      },
      "gridPos": { "h": 8, "w": 8, "x": 16, "y": 6 },
      "fieldConfig": {
        "defaults": {
          "unit": "bytes",
          "custom": {
            "drawStyle": "line",
            "lineInterpolation": "smooth",
            "fillOpacity": 10,
            "gradientMode": "none",
            "spanNulls": false,
            "showPoints": "auto",
            "pointSize": 5,
            "stacking": { "mode": "none", "group": "A" },
            "axisPlacement": "auto",
            "lineWidth": 1
          },
          "color": { "mode": "palette-classic" },
          "thresholds": {
            "mode": "absolute",
            "steps": [
              { "color": "green", "value": null }
            ]
          }
        },
        "overrides": []
      },
      "options": {
        "tooltip": { "mode": "multi", "sort": "desc" },
        "legend": { "displayMode": "list", "placement": "bottom", "calcs": [] }
      },
      "targets": [
        {
          "datasource": {
            "type": "prometheus",
            "uid": "prometheus"
          },
          "expr": "fluentbit_input_storage_memory_bytes{job=~\"$fb_job\",instance=~\"$fb_instance\"}",
          "refId": "A",
          "legendFormat": "{{name}}"
        }
      ]
    },
    {
      "type": "row",
      "title": "Fluent Bit Output",
      "collapsed": false,
      "gridPos": { "h": 1, "w": 24, "x": 0, "y": 14 },
      "id": 102,
      "panels": []
    },
    {
      "type": "timeseries",
      "title": "Output Bytes/sec",
      "id": 10,
      "datasource": {
        "type": "prometheus",
        "uid": "prometheus"
      },
      "gridPos": { "h": 8, "w": 6, "x": 0, "y": 15 },
      "fieldConfig": {
        "defaults": {
          "unit": "Bps",
          "custom": {
            "drawStyle": "line",
            "lineInterpolation": "smooth",
            "fillOpacity": 10,
            "gradientMode": "none",
            "spanNulls": false,
            "showPoints": "auto",
            "pointSize": 5,
            "stacking": { "mode": "none", "group": "A" },
            "axisPlacement": "auto",
            "lineWidth": 1
          },
          "color": { "mode": "palette-classic" },
          "thresholds": {
            "mode": "absolute",
            "steps": [
              { "color": "green", "value": null }
            ]
          }
        },
        "overrides": []
      },
      "options": {
        "tooltip": { "mode": "multi", "sort": "desc" },
        "legend": { "displayMode": "list", "placement": "bottom", "calcs": [] }
      },
      "targets": [
        {
          "datasource": {
            "type": "prometheus",
            "uid": "prometheus"
          },
          "expr": "rate(fluentbit_output_proc_bytes_total{job=~\"$fb_job\",instance=~\"$fb_instance\"}[5m])",
          "refId": "A",
          "legendFormat": "{{name}}"
        }
      ]
    },
    {
      "type": "timeseries",
      "title": "Output Retries/sec",
      "id": 11,
      "datasource": {
        "type": "prometheus",
        "uid": "prometheus"
      },
      "gridPos": { "h": 8, "w": 6, "x": 6, "y": 15 },
      "fieldConfig": {
        "defaults": {
          "unit": "short",
          "custom": {
            "drawStyle": "line",
            "lineInterpolation": "smooth",
            "fillOpacity": 10,
            "gradientMode": "none",
            "spanNulls": false,
            "showPoints": "auto",
            "pointSize": 5,
            "stacking": { "mode": "none", "group": "A" },
            "axisPlacement": "auto",
            "lineWidth": 1
          },
          "color": { "mode": "palette-classic" },
          "thresholds": {
            "mode": "absolute",
            "steps": [
              { "color": "green", "value": null }
            ]
          }
        },
        "overrides": []
      },
      "options": {
        "tooltip": { "mode": "multi", "sort": "desc" },
        "legend": { "displayMode": "list", "placement": "bottom", "calcs": [] }
      },
      "targets": [
        {
          "datasource": {
            "type": "prometheus",
            "uid": "prometheus"
          },
          "expr": "rate(fluentbit_output_retries_total{job=~\"$fb_job\",instance=~\"$fb_instance\"}[5m])",
          "refId": "A",
          "legendFormat": "{{name}}"
        }
      ]
    },
    {
      "type": "timeseries",
      "title": "Output Errors/sec",
      "id": 12,
      "datasource": {
        "type": "prometheus",
        "uid": "prometheus"
      },
      "gridPos": { "h": 8, "w": 6, "x": 12, "y": 15 },
      "fieldConfig": {
        "defaults": {
          "unit": "short",
          "custom": {
            "drawStyle": "line",
            "lineInterpolation": "smooth",
            "fillOpacity": 10,
            "gradientMode": "none",
            "spanNulls": false,
            "showPoints": "auto",
            "pointSize": 5,
            "stacking": { "mode": "none", "group": "A" },
            "axisPlacement": "auto",
            "lineWidth": 1
          },
          "color": { "mode": "palette-classic" },
          "thresholds": {
            "mode": "absolute",
            "steps": [
              { "color": "green", "value": null }
            ]
          }
        },
        "overrides": []
      },
      "options": {
        "tooltip": { "mode": "multi", "sort": "desc" },
        "legend": { "displayMode": "list", "placement": "bottom", "calcs": [] }
      },
      "targets": [
        {
          "datasource": {
            "type": "prometheus",
            "uid": "prometheus"
          },
          "expr": "rate(fluentbit_output_errors_total{job=~\"$fb_job\",instance=~\"$fb_instance\"}[5m])",
          "refId": "A",
          "legendFormat": "{{name}}"
        }
      ]
    },
    {
      "type": "timeseries",
      "title": "Dropped Records/sec",
      "id": 13,
      "datasource": {
        "type": "prometheus",
        "uid": "prometheus"
      },
      "gridPos": { "h": 8, "w": 6, "x": 18, "y": 15 },
      "fieldConfig": {
        "defaults": {
          "unit": "short",
          "custom": {
            "drawStyle": "line",
            "lineInterpolation": "smooth",
            "fillOpacity": 10,
            "gradientMode": "none",
            "spanNulls": false,
            "showPoints": "auto",
            "pointSize": 5,
            "stacking": { "mode": "none", "group": "A" },
            "axisPlacement": "auto",
            "lineWidth": 1
          },
          "color": { "mode": "palette-classic" },
          "thresholds": {
            "mode": "absolute",
            "steps": [
              { "color": "green", "value": null }
            ]
          }
        },
        "overrides": []
      },
      "options": {
        "tooltip": { "mode": "multi", "sort": "desc" },
        "legend": { "displayMode": "list", "placement": "bottom", "calcs": [] }
      },
      "targets": [
        {
          "datasource": {
            "type": "prometheus",
            "uid": "prometheus"
          },
          "expr": "rate(fluentbit_output_dropped_records_total{job=~\"$fb_job\",instance=~\"$fb_instance\"}[5m])",
          "refId": "A",
          "legendFormat": "{{name}}"
        }
      ]
    },
    {
      "type": "row",
      "title": "Fluentd Output",
      "collapsed": false,
      "gridPos": { "h": 1, "w": 24, "x": 0, "y": 23 },
      "id": 103,
      "panels": []
    },
    {
      "type": "timeseries",
      "title": "Buffer Queue Length",
      "id": 14,
      "datasource": {
        "type": "prometheus",
        "uid": "prometheus"
      },
      "gridPos": { "h": 8, "w": 8, "x": 0, "y": 24 },
      "fieldConfig": {
        "defaults": {
          "unit": "short",
          "custom": {
            "drawStyle": "line",
            "lineInterpolation": "smooth",
            "fillOpacity": 10,
            "gradientMode": "none",
            "spanNulls": false,
            "showPoints": "auto",
            "pointSize": 5,
            "stacking": { "mode": "none", "group": "A" },
            "axisPlacement": "auto",
            "lineWidth": 1
          },
          "color": { "mode": "palette-classic" },
          "thresholds": {
            "mode": "absolute",
            "steps": [
              { "color": "green", "value": null }
            ]
          }
        },
        "overrides": []
      },
      "options": {
        "tooltip": { "mode": "multi", "sort": "desc" },
        "legend": { "displayMode": "list", "placement": "bottom", "calcs": [] }
      },
      "targets": [
        {
          "datasource": {
            "type": "prometheus",
            "uid": "prometheus"
          },
          "expr": "fluentd_output_status_buffer_queue_length{job=~\"$fd_job\",instance=~\"$fd_instance\"}",
          "refId": "A",
          "legendFormat": "{{plugin_id}}"
        }
      ]
    },
    {
      "type": "timeseries",
      "title": "Buffer Available Space Ratio",
      "id": 15,
      "datasource": {
        "type": "prometheus",
        "uid": "prometheus"
      },
      "gridPos": { "h": 8, "w": 8, "x": 8, "y": 24 },
      "fieldConfig": {
        "defaults": {
          "unit": "percentunit",
          "custom": {
            "drawStyle": "line",
            "lineInterpolation": "smooth",
            "fillOpacity": 10,
            "gradientMode": "none",
            "spanNulls": false,
            "showPoints": "auto",
            "pointSize": 5,
            "stacking": { "mode": "none", "group": "A" },
            "axisPlacement": "auto",
            "lineWidth": 1
          },
          "color": { "mode": "palette-classic" },
          "thresholds": {
            "mode": "absolute",
            "steps": [
              { "color": "green", "value": null }
            ]
          }
        },
        "overrides": []
      },
      "options": {
        "tooltip": { "mode": "multi", "sort": "desc" },
        "legend": { "displayMode": "list", "placement": "bottom", "calcs": [] }
      },
      "targets": [
        {
          "datasource": {
            "type": "prometheus",
            "uid": "prometheus"
          },
          "expr": "fluentd_output_status_buffer_available_space_ratio{job=~\"$fd_job\",instance=~\"$fd_instance\"}",
          "refId": "A",
          "legendFormat": "{{plugin_id}}"
        }
      ]
    },
    {
      "type": "timeseries",
      "title": "Emit Records/sec",
      "id": 16,
      "datasource": {
        "type": "prometheus",
        "uid": "prometheus"
      },
      "gridPos": { "h": 8, "w": 8, "x": 16, "y": 24 },
      "fieldConfig": {
        "defaults": {
          "unit": "short",
          "custom": {
            "drawStyle": "line",
            "lineInterpolation": "smooth",
            "fillOpacity": 10,
            "gradientMode": "none",
            "spanNulls": false,
            "showPoints": "auto",
            "pointSize": 5,
            "stacking": { "mode": "none", "group": "A" },
            "axisPlacement": "auto",
            "lineWidth": 1
          },
          "color": { "mode": "palette-classic" },
          "thresholds": {
            "mode": "absolute",
            "steps": [
              { "color": "green", "value": null }
            ]
          }
        },
        "overrides": []
      },
      "options": {
        "tooltip": { "mode": "multi", "sort": "desc" },
        "legend": { "displayMode": "list", "placement": "bottom", "calcs": [] }
      },
      "targets": [
        {
          "datasource": {
            "type": "prometheus",
            "uid": "prometheus"
          },
          "expr": "rate(fluentd_output_status_emit_records{job=~\"$fd_job\",instance=~\"$fd_instance\"}[5m])",
          "refId": "A",
          "legendFormat": "{{plugin_id}}"
        }
      ]
    },
    {
      "type": "timeseries",
      "title": "Retry Count",
      "id": 17,
      "datasource": {
        "type": "prometheus",
        "uid": "prometheus"
      },
      "gridPos": { "h": 8, "w": 8, "x": 0, "y": 32 },
      "fieldConfig": {
        "defaults": {
          "unit": "short",
          "custom": {
            "drawStyle": "line",
            "lineInterpolation": "smooth",
            "fillOpacity": 10,
            "gradientMode": "none",
            "spanNulls": false,
            "showPoints": "auto",
            "pointSize": 5,
            "stacking": { "mode": "none", "group": "A" },
            "axisPlacement": "auto",
            "lineWidth": 1
          },
          "color": { "mode": "palette-classic" },
          "thresholds": {
            "mode": "absolute",
            "steps": [
              { "color": "green", "value": null }
            ]
          }
        },
        "overrides": []
      },
      "options": {
        "tooltip": { "mode": "multi", "sort": "desc" },
        "legend": { "displayMode": "list", "placement": "bottom", "calcs": [] }
      },
      "targets": [
        {
          "datasource": {
            "type": "prometheus",
            "uid": "prometheus"
          },
          "expr": "fluentd_output_status_retry_count{job=~\"$fd_job\",instance=~\"$fd_instance\"}",
          "refId": "A",
          "legendFormat": "{{plugin_id}}"
        }
      ]
    },
    {
      "type": "timeseries",
      "title": "Write Count/sec",
      "id": 18,
      "datasource": {
        "type": "prometheus",
        "uid": "prometheus"
      },
      "gridPos": { "h": 8, "w": 8, "x": 8, "y": 32 },
      "fieldConfig": {
        "defaults": {
          "unit": "short",
          "custom": {
            "drawStyle": "line",
            "lineInterpolation": "smooth",
            "fillOpacity": 10,
            "gradientMode": "none",
            "spanNulls": false,
            "showPoints": "auto",
            "pointSize": 5,
            "stacking": { "mode": "none", "group": "A" },
            "axisPlacement": "auto",
            "lineWidth": 1
          },
          "color": { "mode": "palette-classic" },
          "thresholds": {
            "mode": "absolute",
            "steps": [
              { "color": "green", "value": null }
            ]
          }
        },
        "overrides": []
      },
      "options": {
        "tooltip": { "mode": "multi", "sort": "desc" },
        "legend": { "displayMode": "list", "placement": "bottom", "calcs": [] }
      },
      "targets": [
        {
          "datasource": {
            "type": "prometheus",
            "uid": "prometheus"
          },
          "expr": "rate(fluentd_output_status_write_count{job=~\"$fd_job\",instance=~\"$fd_instance\"}[5m])",
          "refId": "A",
          "legendFormat": "{{plugin_id}}"
        }
      ]
    },
    {
      "type": "timeseries",
      "title": "Errors",
      "id": 19,
      "datasource": {
        "type": "prometheus",
        "uid": "prometheus"
      },
      "gridPos": { "h": 8, "w": 8, "x": 16, "y": 32 },
      "fieldConfig": {
        "defaults": {
          "unit": "short",
          "custom": {
            "drawStyle": "line",
            "lineInterpolation": "smooth",
            "fillOpacity": 10,
            "gradientMode": "none",
            "spanNulls": false,
            "showPoints": "auto",
            "pointSize": 5,
            "stacking": { "mode": "none", "group": "A" },
            "axisPlacement": "auto",
            "lineWidth": 1
          },
          "color": { "mode": "thresholds" },
          "thresholds": {
            "mode": "absolute",
            "steps": [
              { "color": "green", "value": null },
              { "color": "red", "value": 1 }
            ]
          }
        },
        "overrides": []
      },
      "options": {
        "tooltip": { "mode": "multi", "sort": "desc" },
        "legend": { "displayMode": "list", "placement": "bottom", "calcs": [] }
      },
      "targets": [
        {
          "datasource": {
            "type": "prometheus",
            "uid": "prometheus"
          },
          "expr": "fluentd_output_status_num_errors{job=~\"$fd_job\",instance=~\"$fd_instance\"}",
          "refId": "A",
          "legendFormat": "{{plugin_id}}"
        }
      ]
    }
  ]
}